charmarr_lib/vpn/__init__.py
charmarr_lib/vpn/_version.py
charmarr_lib/vpn/constants.py
charmarr_lib/vpn/_k8s/__init__.py
charmarr_lib/vpn/_k8s/_gateway.py
charmarr_lib/vpn/_k8s/_gateway_client.py
charmarr_lib/vpn/_k8s/_kill_switch.py
charmarr_lib/vpn/_k8s/_utils.py
charmarr_lib/vpn/interfaces/__init__.py
charmarr_lib/vpn/interfaces/_vpn_gateway.py
charmarr_lib_vpn-0.5.0.dist-info/METADATA
charmarr_lib_vpn-0.5.0.dist-info/WHEEL
charmarr_lib_vpn-0.5.0.dist-info/RECORD
